obsidian_lab.py
obsidian_lab/__init__.py
obsidian_lab/app.py
obsidian_lab-0.2.5.dist-info/LICENSE
obsidian_lab-0.2.5.dist-info/METADATA
obsidian_lab-0.2.5.dist-info/WHEEL
obsidian_lab-0.2.5.dist-info/entry_points.txt
obsidian_lab-0.2.5.dist-info/top_level.txt
obsidian_lab-0.2.5.dist-info/RECORD
