Metadata-Version: 2.1
Name: obsidian-lab
Version: 0.2.5
Summary: Obsidian lab app
Home-page: https://github.com/cristianvasquez/obsidian-lab-py
Author: Cristian Vasquez
License: MIT
Project-URL: Bug Tracker, https://github.com/cristianvasquez/obsidian-lab-py/issues
Platform: UNKNOWN
Classifier: Development Status :: 1 - Planning
Classifier: Environment :: Console
Classifier: Environment :: Plugins
Classifier: Intended Audience :: Science/Research
Requires-Python: >=3.6
Requires-Dist: Flask
Requires-Dist: Flask-Cors
Requires-Dist: Flask-json-schema
